{
    "coverage": {
        "US Census": {
            "geoid": "28023",
            "name": "Clarke County",
            "state": "Mississippi"
        },
        "country": "us",
        "state": "ms",
        "county": "Clarke"
    },
    "schema": 2,
    "layers": {
        "addresses": [
            {
                "name": "county",
                "data": "https://services3.arcgis.com/P2ycm114aIMZgq9f/ArcGIS/rest/services/Clarke_Service/FeatureServer/12",
                "protocol": "ESRI",
                "conform": {
                    "format": "geojson",
                    "number": "STREET_NUM",
                    "street": "STREET"
                }
            }
        ],
        "parcels": [
            {
                "name": "county",
                "data": "https://services3.arcgis.com/P2ycm114aIMZgq9f/ArcGIS/rest/services/Clarke_Service/FeatureServer/12",
                "protocol": "ESRI",
                "conform": {
                    "format": "geojson",
                    "pid": "PARCEL_ID"
                }
            }
        ]
    }
}
