{
    "coverage": {
        "US Census": {
            "geoid": "17163",
            "name": "St. Clair County",
            "state": "Illinois"
        },
        "country": "us",
        "state": "il",
        "county": "St. Clair"
    },
    "data": "http://publicmap.co.st-clair.il.us/gissvr7/rest/services/parcel_viewer/MapServer/36",
    "protocol": "ESRI",
    "conform": {
        "format": "geojson",
        "number": "SITENUM",
        "street": [
            "SITEPREF",
            "SITENAME",
            "SITETYPE",
            "SITESUFF"
        ],
        "unit": "SITEUNIT",
        "city": "SITECITY",
        "postcode": "SITEZIP",
        "region": "SITEST"
    }
}
