{
    "coverage": {
        "US Census": {
            "geoid": "06047",
            "name": "Merced County",
            "state": "California"
        },
        "country": "us",
        "state": "ca",
        "county": "Merced"
    },
    "conform": {
        "type": "geojson",
        "number": "HOUSE_NUM",
        "street": [
            "ST_DIR",
            "ST_NAME",
            "ST_TYPE"
        ]
    },
    "attribution": "Merced County",
    "data": "http://map.co.merced.ca.us/arcgis/rest/services/internet/basemap_web_fire/MapServer/74",
    "type": "ESRI"
}
