{
    "coverage": {
        "country": "ca",
        "state": "on",
        "city": "york region"
    },
    "data": "http://data.openaddresses.io/cache/ca-on-york_region.zip",
    "website": "http://www.york.ca/opendatalist/",
    "attribution": "York Region",
    "type": "http",
    "compression": "zip",
    "conform": {
        "number": ["ADDRESS_NU","ADD_NUM_SU"],
        "street": "FULL_STREE",
        "postcode": "MAIL_POSTA",
        "type": "shapefile"
    },
    "skip": true,
    "note": "cached data not valid zip and will be replaced"
}
