{
    "type": "http",
    "data": "https://downloadagiv.blob.core.windows.net/crab-adressenlijst/Shapefile/CRAB_Adressenlijst.zip",
    "website": "https://download.agiv.be/Producten/Detail?id=447",
    "compression": "zip",
    "coverage": {
        "country": "be",
        "state": "Flanders"
    },
    "license": "https://wiki.openstreetmap.org/wiki/AGIV_CRAB_Import/Free_open_data_licence_Flanders",
    "conform": {
        "file": "Shapefile/CrabAdr.shp",
        "number": "HUISNR",
        "type": "shapefile",
        "encoding": "iso-8859-1",
        "street": "STRAATNM",
        "lon": "X",
        "lat": "Y",
        "srs": "EPSG:31370",
        "headers": 1,
        "skiplines": 1
    }
}
