{
    "coverage": {
        "country": "ca",
        "state": "bc",
        "county": "District of North Vancouver"
    },
    "data": "http://geoweb.dnv.org/Products/Data/CSV/BldAddress_CSV.zip",
    "website": "http://geoweb.dnv.org/data/",
    "license": "http://geoweb.dnv.org/data/#legalModal",
    "note": "Click Legal on website to get license.",
    "type": "http",
    "fingerprint": "219a874507c2ff50da3e32e3fda29e7d",
    "version": "20140804",
    "cache": "http://s3.amazonaws.com/openaddresses/20140804/ca-bc-north_vancouver"
}
