{
    "coverage": {
        "country": "us",
        "state": "fl",
        "county": "Manatee"
    },
    "data": "http://www.mymanatee.org/gisapps/data/shape/parcels.zip",
    "website": "http://www.mymanatee.org/home/government/departments/information-technology/gis-home/gis-datadownload.html",
    "license": "Public Domain",
    "type": "http",
    "compression": "zip",
    "fingerprint": "6cf515de1b625c1d8141ca1922c322bb",
    "version": "20140804",
    "cache": "http://s3.amazonaws.com/openaddresses/20140804/us-fl-manatee.zip"
}