{
    "coverage": {
        "US Census": {"geoid": "17183", "name": "Vermilion County", "state": "Illinois"},
        "country": "us",
        "state": "il",
        "county": "Vermilion"
    },
    "data": "http://services2.bhamaps.com/arcgis/rest/services/AGS_vermilion_co_il_taxmap/MapServer/0",
    "type": "ESRI",
    "fingerprint": "4af76703fa98aa942e71c2e6dc197652",
    "version": "20140804",
    "conform": {
        "split": "FullSiteAddress1",
        "lon": "x",
        "lat": "y",
        "number": "auto_number",
        "street": "auto_street",
        "type": "geojson"
    }
}