{
    "coverage": {
        "US Census": {"geoid": "30065", "name": "Musselshell County", "state": "Montana"},
        "country": "us",
        "state": "mt",
        "county": "Musselshell"
    },
    "data": "ftp://anonymous:anonymous@ftp.gis.mt.gov/CadastralFramework/Musselshell/MusselshellOwnerParcel_shp.zip",
    "type": "ftp",
    "compression": "zip",
    "fingerprint": "4124339be59a1229ba2b0e15938318b7",
    "version": "20140807",
    "cache": "http://s3.amazonaws.com/openaddresses/20140807/us-mt-musselshell.zip",
    "conform": {
        "split": "OwnerAddre",
        "lon": "x",
        "lat": "y",
        "number": "auto_number",
        "street": "auto_street",
        "type": "shapefile-polygon"
    },
    "processed": "http://s3.amazonaws.com/openaddresses/us-mt-musselshell.csv"
}