{
    "coverage": {
        "US Census": {
            "geoid": "28033",
            "name": "DeSoto County",
            "state": "Mississippi"
        },
        "country": "us",
        "state": "ms",
        "county": "DeSoto"
    },
    "data": "http://maps.desotocountyms.gov/arcgis/rest/services/Layers/MapServer/82",
    "type": "ESRI",
    "conform": {
        "split": "YellowMedicineTaxData.dbo.tblParcelJoin.TAXPAYER_ADDRESS",
        "lon": "OA:x",
        "lat": "OA:y",
        "number": "auto_number",
        "street": "auto_street",
        "type": "csv"
    }
}