{
    "coverage": {
        "US Census": {"geoid": "37007", "name": "Anson County", "state": "North Carolina"},
        "country": "us",
        "state": "nc",
        "county": "Anson"
    },
    "data": "http://www.co.anson.nc.us/Portals/2/records/address.zip",
    "type": "http",
    "compression": "zip",
    "website": "http://www.co.anson.nc.us/PublicRecords/GISDataDownloads.aspx",
    "fingerprint": "c6f020a515837ff48c71e94944cb5f60",
    "version": "20140407",
    "cache": "http://s3.amazonaws.com/openaddresses/us-nc-anson.zip",
    "note": "unzip times out"
}
