{
    "coverage": {
        "country": "us",
        "state": "pa",
        "county": "Allegheny"
    },
    "data": "ftp://www.pasda.psu.edu/pub/pasda/alleghenycounty/AlleghenyCounty_AddressPoints201403.zip",
    "license": "",
    "year": "2014-03",
    "type": "ftp",
    "compression": "zip",
    "fingerprint": "934f651ac9564eee5145926f0dd3be0f",
    "version": "20140813",
    "cache": "http://s3.amazonaws.com/openaddresses/20140813/us-pa-allegheny.zip",
    "conform": {
        "merge": [
            "ST_NAME",
            "ST_TYPE"
        ],
        "lon": "x",
        "lat": "y",
        "number": "ADDR_NUM",
        "street": "auto_street",
        "type": "shapefile"
    },
    "processed": "http://s3.amazonaws.com/openaddresses/us-pa-allegheny.csv"
}