{
    "coverage": {
        "country": "us",
        "state": "tx",
        "city": "Round Rock"
    },
    "website": "http://www.roundrocktexas.gov/home/index.asp?page=517",
    "data": "http://www.roundrocktexas.gov/docs/address.zip",
    "license": "Indemnification",
    "year": "2014",
    "type": "http",
    "compression": "zip",
    "fingerprint": "cddf9bcd106602e356672757263c7a6d",
    "version": "20140814",
    "cache": "http://s3.amazonaws.com/openaddresses/20140814/us-tx-round_rock.zip"
}