{
    "coverage": {
        "US Census": {
            "geoid": "55023",
            "name": "Crawford County",
            "state": "Wisconsin"
        },
        "country": "us",
        "state": "wi",
        "county": "Crawford"
    },
    "data": "http://gis2.msa-ps.com/ArcGIS/rest/services/StreetsAddress/MapServer/22",
    "type": "ESRI",
    "conform": {
        "lon": "x",
        "lat": "y",
        "number": "hseno",
        "street": "parcelstre",
        "type": "geojson",
        "postcode": "pzip"
    }
}