{
    "coverage": {
        "US Census": {
            "geoid": "55005",
            "name": "Barron County",
            "state": "Wisconsin"
        },
        "country": "us",
        "state": "wi",
        "county": "Barron"
    },
    "schema": 2,
    "layers": {
        "addresses": [
            {
                "name": "county",
                "data": "https://services9.arcgis.com/ZhDG7T3IrFY4XU9j/arcgis/rest/services/BarronCounty_Parcel_Muni_Add_2025_WISCO/FeatureServer/0",
                "website": "https://beacon.schneidercorp.com/Application.aspx?App=BarronCountyWI&PageType=Map",
                "protocol": "ESRI",
                "conform": {
                    "format": "geojson",
                    "number": "Add_Number",
                    "street": [
                        "St_PreDir",
                        "St_Name",
                        "St_PosTyp",
                        "St_PosDir"
                    ],
                    "unit": "Room",
                    "city": "Post_Comm",
                    "postcode": "Post_Code"
                }
            }
        ],
        "parcels": [
            {
                "name": "county",
                "data": "https://services9.arcgis.com/ZhDG7T3IrFY4XU9j/arcgis/rest/services/BarronCounty_Parcel_Muni_Add_2025_WISCO/FeatureServer/2",
                "website": "https://beacon.schneidercorp.com/Application.aspx?App=BarronCountyWI&PageType=Map",
                "protocol": "ESRI",
                "conform": {
                    "format": "geojson",
                    "pid": "PARCELID"
                }
            }
        ],
        "buildings": [
            {
                "name": "county",
                "data": "https://gisdata.wisc.edu/public/Barron_Buildings_2019.zip",
                "website": "https://geodata.wisc.edu/catalog/F7AB738D-968B-4A6C-B7AF-63E819EFBDDC",
                "protocol": "http",
                "compression": "zip",
                "year": "2019",
                "conform": {
                    "format": "gdb",
                    "layer": "Barron_Buildings_2019"
                }
            }
        ]
    }
}
