{
    "coverage": {
        "US Census": {
            "geoid": "55077",
            "name": "Marquette County",
            "state": "Wisconsin"
        },
        "country": "us",
        "state": "wi",
        "county": "Marquette"
    },
    "schema": 2,
    "layers": {
        "addresses": [
            {
                "name": "county",
                "data": "https://webportal.co.marquette.wi.us/publicags/rest/services/Geovalidation/ProductionA/MapServer/0",
                "protocol": "ESRI",
                "conform": {
                    "format": "geojson",
                    "number": "HouseNum",
                    "street": [
                        "PreDir",
                        "StreetName",
                        "StreetType"
                    ]
                }
            }
        ],
        "centerlines": [
            {
                "name": "county",
                "data": "https://webportal.co.marquette.wi.us/publicags/rest/services/Transportation/Roads2/FeatureServer/0",
                "protocol": "ESRI",
                "conform": {
                    "format": "geojson",
                    "name": "FullStNm",
                    "addr_from_left": "FromAddr_L",
                    "addr_to_left": "ToAddr_L",
                    "addr_from_right": "FromAddr_R",
                    "addr_to_right": "ToAddr_R",
                    "zip_left": "PostCode_L",
                    "zip_right": "PostCode_R",
                    "speed": "SpeedLimit",
                    "oneway": "OneWay"
                }
            }
        ],
        "parcels": [
            {
                "name": "county",
                "data": "https://webportal.co.marquette.wi.us/publicags/rest/services/AssessmentInformation/TaxParcels/FeatureServer/0",
                "protocol": "ESRI",
                "conform": {
                    "format": "geojson",
                    "pid": "PARCELID"
                }
            }
        ]
    }
}
