{
    "coverage": {
        "US Census": {
            "geoid": "29077",
            "name": "Greene County",
            "state": "Missouri"
        },
        "country": "us",
        "state": "mo",
        "county": "Greene"
    },
    "data": "https://maps.springfieldmo.gov/arcgis/rest/services/Maps/OpenData/MapServer/0",
    "protocol": "ESRI",
    "conform": {
        "format": "geojson",
        "number": [
            "prim_num",
            "SUB_NUM"
        ],
        "street": [
            "PRE_DIR",
            "str_nam",
            "str_type",
            "SUF_DIR"
        ],
        "unit": [
            "UNIT_TYPE",
            "UNIT_NUM"
        ],
        "city": "CITY",
        "region": "STATE",
        "postcode": "zip5"
    }
}
