{
    "coverage": {
        "US Census": {
            "geoid": "24003",
            "name": "Anne Arundel County",
            "state": "Maryland"
        },
        "country": "us",
        "state": "md",
        "county": "anne arundel"
    },
    "data": "http://gis-world3.aacounty.org/arcgis/rest/services/Public/StreetViewer/MapServer/0",
    "website": "http://www.aacounty.org/departments/planning-and-zoning/research-and-gis/",
    "attribution": "Anne Arundel County",
    "protocol": "ESRI",
    "conform": {
        "format": "geojson",
        "number": "ST_NUMBER",
        "street": [
            "ST_PREFIXD",
            "ST_NAME",
            "ST_TYPE",
            "ST_SUFFIXD"
        ],
        "unit": "ST_NUMSUFF",
        "city": "CITY_NAME",
        "postcode": "ZIPCODE",
        "addrtype": "BLDG_CODE"
    }
}
