{
    "coverage": {
        "US Census": {
            "geoid": "21019",
            "name": "Boyd County",
            "state": "Kentucky"
        },
        "country": "us",
        "state": "ky"
    },
    "layers": {
        "addresses": [
            {
                "type": "http",
                "data": "https://s3.amazonaws.com/data.openaddresses.io/cache/uploads/iandees/4c9049/MasterAddresses.zip",
                "conform": {
                    "type": "shapefile",
                    "number": "NUMBER",
                    "street": "STREET"
                },
                "compression": "zip",
                "note": "Shapefile received from Sandy Ott, http://boydcounty911.com/"
            }
        ],
        "buildings": []
    }
}