{
    "coverage": {
        "US Census": {
            "geoid": "32005",
            "name": "Douglas County",
            "state": "Nevada"
        },
        "country": "us",
        "state": "nv",
        "county": "Douglas"
    },
    "schema": 2,
    "layers": {
        "addresses": [
            {
                "name": "county",
                "data": "https://gisservices.douglasnv.us/varcgis/rest/services/Hosted/Addresses_Feature_Service/FeatureServer/1",
                "protocol": "ESRI",
                "conform": {
                    "format": "geojson",
                    "unit": "unit",
                    "number": "numb",
                    "street": "street"
                }
            }
        ]
    }
}
