{
    "coverage": {
        "country": "kr",
        "city": "중랑구",
        "state": "seoul",
        "geometry": {
            "type": "Point",
            "coordinates": [
                127.092,
                37.598
            ]
        }
    },
    "layers": {
        "addresses": [
            {
                "type": "http",
                "data": "http://s3.amazonaws.com/data.openaddresses.io/cache/kr-seoul-chungnanggu.zip",
                "website": "http://data.seoul.go.kr/openinf/sheetview.jsp?infId=OA-1090",
                "conform": {
                    "skiplines": 2,
                    "encoding": "EUCKR",
                    "lon": "POINT_X",
                    "srs": "EPSG:2097",
                    "headers": 2,
                    "street": {
                        "function": "join",
                        "fields": [
                            "RD_NM",
                            "BD_NM",
                            "DET_BD_NM"
                        ],
                        "separator": " "
                    },
                    "lat": "POINT_Y",
                    "type": "csv",
                    "number": "LNDN_MA_SN"
                },
                "compression": "zip",
                "license": {
                    "text": "CCBY",
                    "attribution": true,
                    "share-alike": false
                },
                "note": "TOS acceptance means files must be manually downloaded. Proof of license present in expandable section near top of dataset webpage.",
                "skip": true
            }
        ],
        "buildings": []
    }
}