{
    "coverage": {
        "US Census": {
            "geoid": "48493",
            "name": "Wilson County",
            "state": "Texas"
        },
        "country": "us",
        "state": "tx",
        "county": "Wilson"
    },
    "data": "http://mapsatbis.com/bisgis/rest/services/WilsonWeb/MapServer/0",
    "protocol": "ESRI",
    "conform": {
        "format": "geojson",
        "number": "WilsonCad.DBO.Accounts.situs_num",
        "street": [
            "WilsonCad.DBO.Accounts.situs_street_prefx",
            "WilsonCad.DBO.Accounts.situs_street",
            "WilsonCad.DBO.Accounts.situs_street_sufix"
        ],
        "city": "WilsonCad.DBO.Accounts.situs_city",
        "region": "WilsonCad.DBO.Accounts.situs_state",
        "postcode": "WilsonCad.DBO.Accounts.situs_zip"
    }
}
