{
    "coverage": {
        "US Census": {
            "geoid": "48503",
            "name": "Young County",
            "state": "Texas"
        },
        "country": "us",
        "state": "tx",
        "county": "Young"
    },
    "data": "http://mapsatbis.com/bisgis/rest/services/YoungWeb/MapServer/0",
    "type": "ESRI",
    "conform": {
        "number": "YoungCad.dbo.Accounts.situs_num",
        "street": [
            "YoungCad.dbo.Accounts.situs_street_prefx",
            "YoungCad.dbo.Accounts.situs_street",
            "YoungCad.dbo.Accounts.situs_street_sufix"
        ],
        "city": "YoungCad.dbo.Accounts.situs_city",
        "region": "YoungCad.dbo.Accounts.situs_state",
        "postcode": "YoungCad.dbo.Accounts.situs_zip",
        "type": "geojson"
    }
}
