{
    "coverage": {
        "US Census": {
            "geoid": "51079",
            "name": "Greene County",
            "state": "Virginia"
        },
        "country": "us",
        "state": "va",
        "county": "Greene"
    },
    "data": "https://www.webgis.net/arcgis/rest/services/VA/GreeneCo_WebGIS/MapServer/3",
    "type": "ESRI",
    "conform": {
        "type": "geojson",
        "number": "ADDRNUM",
        "street": "FULLNAME",
        "unit": [
            "UNITTYPE",
            "UNITID"
        ],
        "city": "MUNICIPALITY"
    }
}
