{
    "coverage": {
        "country": "ca",
        "state": "bc",
        "county": "East Kootenay",
        "geometry": {
            "type": "Point",
            "coordinates": [
                -115.772,
                50.68
            ]
        }
    },
    "schema": 2,
    "layers": {
        "addresses": [
            {
                "name": "county",
                "data": "https://services1.arcgis.com/SsOSFuyUWJh1AOU5/ArcGIS/rest/services/Civic_Address_Points/FeatureServer/0",
                "website": "https://data3-ca5c0-rdek.opendata.arcgis.com/datasets/RDEK::civic-address-points/about",
                "license": {
                    "text": "Open Government License – Regional District of East Kootenay",
                    "attribution": true,
                    "attribution name": "Regional District of East Kootenay",
                    "share-alike": false
                },
                "protocol": "ESRI",
                "conform": {
                    "format": "geojson",
                    "number": "TextString",
                    "street": "STREET",
                    "unit": "Unit_Number"
                }
            }
        ],
        "parcels": [
            {
                "name": "county",
                "data": "https://services1.arcgis.com/SsOSFuyUWJh1AOU5/arcgis/rest/services/Legal_Parcels/FeatureServer/0",
                "website": "https://data3-ca5c0-rdek.opendata.arcgis.com/datasets/RDEK::legal-parcels/about",
                "license": {
                    "text": "Open Government License – Regional District of East Kootenay",
                    "attribution": true,
                    "attribution name": "Regional District of East Kootenay",
                    "share-alike": false
                },
                "protocol": "ESRI",
                "conform": {
                    "format": "geojson",
                    "pid": "PID"
                }
            }
        ]
    }
}
