{
    "coverage": {
        "country": "ca",
        "state": "bc",
        "county": "Regional District of Okanagan-Similkameen"
    },
    "schema": 2,
    "layers": {
        "addresses": [
            {
                "name": "county",
                "data": "https://opendata.arcgis.com/datasets/4c25dc8ce91248cd8b4fb435bc4ecf35_0.zip?outSR=%7B%22wkt%22%3A%22PROJCS%5B%5C%22NAD_1983_Albers%5C%22%2CGEOGCS%5B%5C%22GCS_North_American_1983%5C%22%2CDATUM%5B%5C%22D_North_American_1983%5C%22%2CSPHEROID%5B%5C%22GRS_1980%5C%22%2C6378137.0%2C298.257222101%5D%5D%2CPRIMEM%5B%5C%22Greenwich%5C%22%2C0.0%5D%2CUNIT%5B%5C%22Degree%5C%22%2C0.0174532925199433%5D%5D%2CPROJECTION%5B%5C%22Albers%5C%22%5D%2CPARAMETER%5B%5C%22False_Easting%5C%22%2C1000000.0%5D%2CPARAMETER%5B%5C%22False_Northing%5C%22%2C0.0%5D%2CPARAMETER%5B%5C%22Central_Meridian%5C%22%2C-126.0%5D%2CPARAMETER%5B%5C%22Standard_Parallel_1%5C%22%2C50.0%5D%2CPARAMETER%5B%5C%22Standard_Parallel_2%5C%22%2C58.5%5D%2CPARAMETER%5B%5C%22Latitude_Of_Origin%5C%22%2C45.0%5D%2CUNIT%5B%5C%22Meter%5C%22%2C1.0%5D%5D%22%7D",
                "website": "http://hub-rdos.opendata.arcgis.com/datasets/cadastral-1?showData=true",
                "license": {
                    "url": "http://www.rdos.bc.ca/departments/information-services/open-data-downloads/terms-of-use/",
                    "text": "Contains information licensed under the Open Government Licence – Regional District Okanagan Similkameen",
                    "attribution": true,
                    "share-alike": false
                },
                "protocol": "http",
                "compression": "zip",
                "conform": {
                    "file": "IS/parcelUpdate/export2FTP/finalExportFolder/parcel_legal_civic_shp_20151007.shp",
                    "number": "civicnum1",
                    "street": "streetnam1",
                    "format": "shapefile-polygon",
                    "id": "PID"
                },
                "skip": true,
                "note": "New data file contains multiple address fields. Unclear if any are physical address"
            }
        ]
    }
}
