{
    "coverage": {
        "country": "ca",
        "state": "bc",
        "county": "District of Sunshine Coast",
        "geometry": {
            "type": "Point",
            "coordinates": [
                -124.296,
                49.855
            ]
        }
    },
    "schema": 2,
    "layers": {
        "addresses": [
            {
                "name": "county",
                "data": "https://opendata.arcgis.com/datasets/e62379e68ea54dfa8faf2765aae927d1_0.zip",
                "website": "http://data-myscrd.opendata.arcgis.com/datasets/e62379e68ea54dfa8faf2765aae927d1_0",
                "protocol": "http",
                "compression": "zip",
                "conform": {
                    "format": "shapefile",
                    "id": "OBJECT_ID",
                    "number": [
                        "STR_NO_PRE",
                        "STR_NO",
                        "STR_NO_SUF"
                    ],
                    "street": [
                        "STR_DR_PRE",
                        "STR_NAME",
                        "STR_TYPE",
                        "STR_DR_SUF"
                    ],
                    "city": "LOCALITY",
                    "postcode": "POST_CODE"
                }
            }
        ]
    }
}
