{
    "coverage": {
        "US Census": {
            "geoid": "01065",
            "name": "Hale County",
            "state": "Alabama"
        },
        "country": "us",
        "state": "al",
        "county": "Hale"
    },
    "schema": 2,
    "layers": {
        "parcels": [
            {
                "name": "county",
                "data": "https://maps.capturecama.com/arcgis/rest/services/Hale/HALE_11132024/MapServer/921",
                "protocol": "ESRI",
                "conform": {
                    "format": "geojson",
                    "pid": "PARCELID"
                }
            }
        ]
    }
}
