{
    "coverage": {
        "US Census": {
            "geoid": "37019",
            "name": "Brunswick County",
            "state": "North Carolina"
        },
        "country": "us",
        "state": "nc",
        "county": "Brunswick"
    },
    "data": "http://www.brunswickcountync.gov/gis/files/2015/07/Structures.zip",
    "type": "http",
    "compression": "zip",
    "conform": {
        "type": "shapefile",
        "number": "ST_NUMB",
        "street": "ST_NAME",
        "unit": "UNIT_NO",
        "city": "POSTAL"
    }
}
