{
    "coverage": {
        "geometry": {
            "type": "Point",
            "coordinates": [
                -79.109,
                35.921
            ]
        },
        "country": "us",
        "state": "nc",
        "town": "Chapel Hill"
    },
    "layers": {
        "addresses": [
            {
                "type": "ESRI",
                "data": "https://gisweb.townofchapelhill.org/arcgis/rest/services/CorporateData/AddressPoints/MapServer/0",
                "website": "http://gis.townofchapelhill.org/download_data/",
                "conform": {
                    "type": "geojson",
                    "number": "HouseNum",
                    "street": [
                        "DirPrefix",
                        "Name",
                        "Type",
                        "DirSuffix"
                    ],
                    "unit": "UnitNum",
                    "region": "State"
                }
            }
        ],
        "buildings": []
    }
}