{
    "coverage": {
        "US Census": {
            "geoid": "41011",
            "name": "Coos County",
            "state": "Oregon"
        },
        "country": "us",
        "state": "or",
        "county": "Coos"
    },
    "data": "https://s3.amazonaws.com/data.openaddresses.io/cache/uploads/migurski/d5add2/oregon_state_addresses.zip",
    "type": "http",
    "compression": "zip",
    "conform": {
        "type": "gdb",
        "file": "Delivery/addresses_oregon.gdb",
        "layer": "Coos",
        "number": {
            "function": "prefixed_number",
            "field": "SITUSSTR"
        },
        "street": {
            "function": "postfixed_street",
            "field": "SITUSSTR"
        },
        "city": "SITUSCITY",
        "postcode": "SITUSZIP"
    }
}
