{
    "coverage": {
        "US Census": {
            "geoid": "41027",
            "name": "Hood River County",
            "state": "Oregon"
        },
        "country": "us",
        "state": "or",
        "county": "Hood River"
    },
    "schema": 2,
    "layers": {
        "addresses": [
            {
                "name": "county",
                "protocol": "ESRI",
                "data": "http://webmap.co.hood-river.or.us/arcgis/rest/services/AllDataLayers/MapServer/1",
                "conform": {
                    "format": "geojson",
                    "number": "HOUSE_NUMBER",
                    "street": [
                        "PREFIX_DIRECTION",
                        "STREET_NAME",
                        "STREET_TYPE"
                    ],
                    "unit": "UNIT"
                }
            }
        ]
    }
}