{
    "coverage": {
        "US Census": {
            "geoid": "41065",
            "state": "Oregon",
            "name": "Wasco County"
        },
        "country": "us",
        "state": "or",
        "county": "Wasco"
    },
    "schema": 2,
    "layers": {
        "addresses": [
            {
                "name": "county",
                "data": "http://216.110.207.61/arcgis/rest/services/BaseMap/MapServer/8",
                "protocol": "ESRI",
                "conform": {
                    "format": "geojson",
                    "number": "STRUCTNO",
                    "street": [
                        "PREDIR",
                        "PRETYPE",
                        "STREETNAME",
                        "STREETTYPE",
                        "SUFDIR"
                    ],
                    "unit": [
                        "UNIT_TYPE",
                        "UNIT_NO"
                    ],
                    "id": "STRUCTNO"
                }
            }
        ]
    }
}