{
    "type": "http",
    "data": "http://www.wien.gv.at/wohnen/baupolizei/csv/gebadr.csv",
    "license": {
        "attribution": "unknown"
    },
    "contact": {
        "email": "t@t.com"
    },
    "note": {
        "update frequency": "daily"
    },
    "conform": {
        "type": "csv",
        "number": {},
        "street": {},
        "unit": {},
        "city": {},
        "district": {},
        "region": {},
        "postcode": {},
        "lon": "N",
        "lat": "N"
    },
    "coverage": {
        "country": "xx"
    }
}